LICENSE
MANIFEST
MANIFEST.in
README.rst
requirements.txt
setup.cfg
setup.py
gradient_api/__init__.py
gradient_api/gradient.py
gradient_api.egg-info/PKG-INFO
gradient_api.egg-info/SOURCES.txt
gradient_api.egg-info/dependency_links.txt
gradient_api.egg-info/not-zip-safe
gradient_api.egg-info/requires.txt
gradient_api.egg-info/top_level.txt