Metadata-Version: 1.1
Name: gradient_api
Version: 1.2.2
Summary: API of gradient descent.
Home-page: https://github.com/shinalone/gradient_api
Author: UlionTse
Author-email: shinalone@outlook.com
License: MIT
Keywords: gradient_api,Gradient,gradient,GradientApi,gradientAPI
Platform: UNKNOWN
Classifier: Development Status :: 4 - Beta
Classifier: Environment :: Web Environment
Classifier: Intended Audience :: Developers
Classifier: License :: OSI Approved :: MIT License
Classifier: Programming Language :: Python :: 3.4
Classifier: Programming Language :: Python :: 3.5
Classifier: Programming Language :: Python :: 3.6
